common/__init__.py
apitoolkit_common-0.1.0.dist-info/METADATA
apitoolkit_common-0.1.0.dist-info/WHEEL
apitoolkit_common-0.1.0.dist-info/top_level.txt
apitoolkit_common-0.1.0.dist-info/RECORD
