Metadata-Version: 2.1
Name: apitoolkit-common
Version: 0.1.0
Summary: Shared code for apitoolkit python sdks
Home-page: https://github.com/apitoolkit/apitoolkit-python
Author: Yussif Mohammed
Author-email: yousiph77@gmail.com
Classifier: Programming Language :: Python :: 3
Classifier: License :: OSI Approved :: MIT License
Classifier: Operating System :: OS Independent
Requires-Python: >=3.7
Requires-Dist: opentelemetry-api>=1.0.0
Requires-Dist: requests>=2.0.0
Requires-Dist: pytz>=2020.1
Requires-Dist: jsonpath-ng>=1.5.3
Requires-Dist: httpx>=0.18.0
